{
  "id": "",
  "name": "",
  "font_family": "iconfont",
  "css_prefix_text": "icon-",
  "description": "",
  "glyphs": [
    {
      "icon_id": "15838429",
      "name": "arrow-down",
      "font_class": "arrow-down",
      "unicode": "e665",
      "unicode_decimal": 58981
    },
    {
      "icon_id": "15838430",
      "name": "ashbin",
      "font_class": "ashbin",
      "unicode": "e666",
      "unicode_decimal": 58982
    },
    {
      "icon_id": "15838431",
      "name": "arrow-right",
      "font_class": "arrow-right",
      "unicode": "e667",
      "unicode_decimal": 58983
    },
    {
      "icon_id": "15838432",
      "name": "browse",
      "font_class": "browse",
      "unicode": "e668",
      "unicode_decimal": 58984
    },
    {
      "icon_id": "15838433",
      "name": "bottom",
      "font_class": "bottom",
      "unicode": "e669",
      "unicode_decimal": 58985
    },
    {
      "icon_id": "15838436",
      "name": "arrow-double-left",
      "font_class": "arrow-double-left",
      "unicode": "e66a",
      "unicode_decimal": 58986
    },
    {
      "icon_id": "15838463",
      "name": "direction-left",
      "font_class": "direction-left",
      "unicode": "e66c",
      "unicode_decimal": 58988
    },
    {
      "icon_id": "15838474",
      "name": "favorite",
      "font_class": "favorite",
      "unicode": "e66f",
      "unicode_decimal": 58991
    },
    {
      "icon_id": "15838484",
      "name": "hide",
      "font_class": "hide",
      "unicode": "e673",
      "unicode_decimal": 58995
    },
    {
      "icon_id": "15838498",
      "name": "fullscreen-expand",
      "font_class": "fullscreen-expand",
      "unicode": "e675",
      "unicode_decimal": 58997
    },
    {
      "icon_id": "15838500",
      "name": "meh",
      "font_class": "meh",
      "unicode": "e677",
      "unicode_decimal": 58999
    },
    {
      "icon_id": "15838505",
      "name": "modular",
      "font_class": "modular",
      "unicode": "e678",
      "unicode_decimal": 59000
    },
    {
      "icon_id": "15838506",
      "name": "notification",
      "font_class": "notification",
      "unicode": "e679",
      "unicode_decimal": 59001
    },
    {
      "icon_id": "15838507",
      "name": "mic",
      "font_class": "mic",
      "unicode": "e67a",
      "unicode_decimal": 59002
    },
    {
      "icon_id": "15838540",
      "name": "time",
      "font_class": "time",
      "unicode": "e680",
      "unicode_decimal": 59008
    },
    {
      "icon_id": "15838561",
      "name": "arrow-left-bold",
      "font_class": "arrow-left-bold",
      "unicode": "e685",
      "unicode_decimal": 59013
    },
    {
      "icon_id": "15838563",
      "name": "close-bold",
      "font_class": "close-bold",
      "unicode": "e686",
      "unicode_decimal": 59014
    },
    {
      "icon_id": "15838564",
      "name": "arrow-down-bold",
      "font_class": "arrow-down-bold",
      "unicode": "e687",
      "unicode_decimal": 59015
    },
    {
      "icon_id": "15838566",
      "name": "arrow-right-bold",
      "font_class": "arrow-right-bold",
      "unicode": "e688",
      "unicode_decimal": 59016
    },
    {
      "icon_id": "15838567",
      "name": "select-bold",
      "font_class": "select-bold",
      "unicode": "e689",
      "unicode_decimal": 59017
    },
    {
      "icon_id": "15838601",
      "name": "fullscreen-expand-filling",
      "font_class": "fullscreen-expand-filling",
      "unicode": "e68a",
      "unicode_decimal": 59018
    },
    {
      "icon_id": "17030229",
      "name": "转交 (2)",
      "font_class": "zhuanjiao2",
      "unicode": "e6d8",
      "unicode_decimal": 59096
    },
    {
      "icon_id": "17030233",
      "name": "字典管理 (5)",
      "font_class": "zidianguanli5",
      "unicode": "e6d9",
      "unicode_decimal": 59097
    },
    {
      "icon_id": "17030238",
      "name": "最新完结",
      "font_class": "zuixinwanjie",
      "unicode": "e6da",
      "unicode_decimal": 59098
    },
    {
      "icon_id": "18795965",
      "name": "法律审查",
      "font_class": "weibiaoti-4",
      "unicode": "e601",
      "unicode_decimal": 58881
    },
    {
      "icon_id": "18796106",
      "name": "制度评审",
      "font_class": "zhidupingshen",
      "unicode": "e602",
      "unicode_decimal": 58882
    },
    {
      "icon_id": "18796332",
      "name": "部门公告",
      "font_class": "bumengonggao",
      "unicode": "e603",
      "unicode_decimal": 58883
    },
    {
      "icon_id": "18796333",
      "name": "洗钱审查",
      "font_class": "xiqianshencha",
      "unicode": "e604",
      "unicode_decimal": 58884
    },
    {
      "icon_id": "18797120",
      "name": "发布时间",
      "font_class": "fabushijian",
      "unicode": "e606",
      "unicode_decimal": 58886
    },
    {
      "icon_id": "18797122",
      "name": "关键词",
      "font_class": "guanjianci",
      "unicode": "e607",
      "unicode_decimal": 58887
    }
  ]
}
